get_reader.py
get_reader-1.0.0.dist-info/METADATA
get_reader-1.0.0.dist-info/WHEEL
get_reader-1.0.0.dist-info/top_level.txt
get_reader-1.0.0.dist-info/RECORD
