Metadata-Version: 2.1
Name: get-reader
Version: 1.0.0
Summary: get_reader() returns csv.reader-like objects from multiple sources
Home-page: https://github.com/shawnbrown/get_reader
Author: Shawn Brown
Author-email: shawnbrown@users.noreply.github.com
License: Apache 2.0
Platform: UNKNOWN
Classifier: License :: OSI Approved :: Apache Software License
Classifier: Development Status :: 5 - Production/Stable
Classifier: Programming Language :: Python :: 2
Classifier: Programming Language :: Python :: 2.6
Classifier: Programming Language :: Python :: 2.7
Classifier: Programming Language :: Python :: 3
Classifier: Programming Language :: Python :: 3.2
Classifier: Programming Language :: Python :: 3.3
Classifier: Programming Language :: Python :: 3.4
Classifier: Programming Language :: Python :: 3.5
Classifier: Programming Language :: Python :: 3.6
Classifier: Programming Language :: Python :: 3.7
Classifier: Programming Language :: Python :: 3.8
Classifier: Programming Language :: Python :: Implementation :: CPython
Classifier: Programming Language :: Python :: Implementation :: PyPy
Classifier: Programming Language :: Python :: Implementation :: Jython
Classifier: Operating System :: OS Independent
Classifier: Topic :: Utilities
Requires-Python: >=2.6.*, !=3.0.*, !=3.1.*
Provides-Extra: dbf
Requires-Dist: dbfread ; extra == 'dbf'
Provides-Extra: excel
Requires-Dist: xlrd ; extra == 'excel'
